fundamentus/__init__.py
fundamentus/_version.py
fundamentus/contracts/__init__.py
fundamentus/contracts/extract_contract.py
fundamentus/contracts/information_contract.py
fundamentus/contracts/mocks/__init__.py
fundamentus/contracts/mocks/extract_contract.py
fundamentus/contracts/mocks/extract_contract_companies.py
fundamentus/contracts/mocks/extract_contract_property_funds.py
fundamentus/contracts/request_contract.py
fundamentus/contracts/transform_contract.py
fundamentus/drivers/__init__.py
fundamentus/drivers/html_collector.py
fundamentus/drivers/html_collector_test.py
fundamentus/drivers/http_requester.py
fundamentus/drivers/http_requester_test.py
fundamentus/drivers/interfaces/__init__.py
fundamentus/drivers/interfaces/html_collector.py
fundamentus/drivers/interfaces/http_requester.py
fundamentus/drivers/mocks/__init__.py
fundamentus/drivers/mocks/companies_list.py
fundamentus/drivers/mocks/html_collector.py
fundamentus/drivers/mocks/http_requester.py
fundamentus/exceptions/__init__.py
fundamentus/exceptions/extract_exception.py
fundamentus/exceptions/http_request_error.py
fundamentus/exceptions/transform_exception.py
fundamentus/main/__init__.py
fundamentus/main/fundamentus_pipeline.py
fundamentus/main/fundamentus_pipeline_test.py
fundamentus/stages/__init__.py
fundamentus/stages/extraction/__init__.py
fundamentus/stages/extraction/extractor_html_information.py
fundamentus/stages/extraction/extractor_html_information_test.py
fundamentus/stages/transformation/__init__.py
fundamentus/stages/transformation/transform_raw_information.py
fundamentus/stages/transformation/transform_raw_information_test.py
fundamentus/utilities/__init__.py
fundamentus/utilities/config.py
fundamentus/utilities/indicator_names.py
fundamentus/utilities/random_user_agent.py
fundamentus/utilities/random_user_agent_test.py
pyfundamentus-0.0.12.dist-info/LICENSE
pyfundamentus-0.0.12.dist-info/METADATA
pyfundamentus-0.0.12.dist-info/WHEEL
pyfundamentus-0.0.12.dist-info/RECORD
