Metadata-Version: 2.1
Name: pyfundamentus
Version: 0.0.12
Summary: Python Fundamentus is a Python API that allows you to quickly access the main fundamental indicators of the main stocks in the Brazilian market.
Home-page: https://github.com/alexcamargos/pyFundamentus
License: MIT
Keywords: stock market,scraping,financial information,fundamentalist information
Author: Alexsander Lopes Camargos
Author-email: alexcamargos@gmail.com
Requires-Python: >=3.7,<4.0
Classifier: Development Status :: 3 - Alpha
Classifier: License :: OSI Approved :: MIT License
Classifier: Operating System :: OS Independent
Classifier: Programming Language :: Python :: 3
Classifier: Programming Language :: Python :: 3.7
Classifier: Programming Language :: Python :: 3.8
Classifier: Programming Language :: Python :: 3.9
Classifier: Programming Language :: Python :: 3.10
Classifier: Programming Language :: Python :: 3.11
Classifier: Programming Language :: Python :: 3.12
Requires-Dist: beautifulsoup4 (>=4.11.1,<5.0.0)
Requires-Dist: requests (==2.28.1)
Requires-Dist: requests-cache (>=0.9.6,<0.10.0)
Project-URL: Repository, https://github.com/alexcamargos/pyFundamentus
